snappy_mpu6050/__init__.py
snappy_mpu6050/_version.py
snappy_mpu6050/i2c.py
snappy_mpu6050-1.0.0.dist-info/DESCRIPTION.rst
snappy_mpu6050-1.0.0.dist-info/METADATA
snappy_mpu6050-1.0.0.dist-info/RECORD
snappy_mpu6050-1.0.0.dist-info/WHEEL
snappy_mpu6050-1.0.0.dist-info/metadata.json
snappy_mpu6050-1.0.0.dist-info/pbr.json
snappy_mpu6050-1.0.0.dist-info/top_level.txt
