Metadata-Version: 2.0
Name: snappy-mpu6050
Version: 1.0.0
Summary: Synapse SNAPpy library for Ivensense MPU-6050 6-axis accelerometer/gyro
Home-page: https://github.com/tylercrumpton/snappy-mpu6050
Author: Tyler Crumpton
Author-email: tyler.crumpton@gmail.com
License: UNKNOWN
Platform: UNKNOWN
Classifier: Development Status :: 1 - Planning
Classifier: Environment :: Console
Classifier: Intended Audience :: Developers
Classifier: Operating System :: POSIX
Classifier: Programming Language :: Python :: 2.7
Classifier: Natural Language :: English
